setup.py
porkchop/__init__.py
porkchop/backend.py
porkchop/commandline.py
porkchop/plugin.py
porkchop/server.py
porkchop/util.py
porkchop.egg-info/PKG-INFO
porkchop.egg-info/SOURCES.txt
porkchop.egg-info/dependency_links.txt
porkchop.egg-info/entry_points.txt
porkchop.egg-info/not-zip-safe
porkchop.egg-info/requires.txt
porkchop.egg-info/top_level.txt
porkchop/plugins/__init__.py
porkchop/plugins/apache.py
porkchop/plugins/cpu.py
porkchop/plugins/cpuinfo.py
porkchop/plugins/df.py
porkchop/plugins/diskstats.py
porkchop/plugins/elasticsearch.py
porkchop/plugins/facter.py
porkchop/plugins/haproxy.py
porkchop/plugins/loadavg.py
porkchop/plugins/memcached.py
porkchop/plugins/meminfo.py
porkchop/plugins/netproto.py
porkchop/plugins/networkinterface.py
porkchop/plugins/openafs.py
porkchop/plugins/openfiles.py
porkchop/plugins/pgbouncer.py
porkchop/plugins/postgresql.py
porkchop/plugins/processes.py
porkchop/plugins/rabbitmq.py
porkchop/plugins/redis.py
porkchop/plugins/riak.py
porkchop/plugins/runit.py
porkchop/plugins/tcpudp.py
porkchop/plugins/test.py
porkchop/plugins/varnish.py