Metadata-Version: 1.0
Name: porkchop
Version: 0.7.3
Summary: Porkchop is a simple HTTP-based system information server
Home-page: http://github.com/disqus/porkchop
Author: Scott Smith
Author-email: scott@disqus.com
License: Apache 2.0
Platform: UNKNOWN
Classifier: Development Status :: 3 - Alpha
Classifier: Intended Audience :: System Administrators
Classifier: License :: OSI Approved :: Apache Software License
Classifier: Topic :: System :: Networking :: Monitoring
